py_promptkit/__init__.py
py_promptkit/errors.py
py_promptkit/loader.py
py_promptkit/runner.py
py_promptkit/litellm/__init__.py
py_promptkit/litellm/core.py
py_promptkit/litellm/mcp_client.py
py_promptkit/litellm/sse_transport.py
py_promptkit/litellm/stdio_transport.py
py_promptkit/litellm/tools.py
py_promptkit/litellm/transport.py
py_promptkit/models/clients.py
py_promptkit/models/config.py
py_promptkit/models/hooks.py
py_promptkit/models/llms.py
py_promptkit/models/transport.py
py_promptkit/utils/_cast.py
py_promptkit/utils/_field.py
py_promptkit/utils/_logger.py
py_promptkit/utils/_type_safety.py
py_promptkit-0.1.0.dist-info/licenses/LICENSE
py_promptkit-0.1.0.dist-info/METADATA
py_promptkit-0.1.0.dist-info/WHEEL
py_promptkit-0.1.0.dist-info/top_level.txt
py_promptkit-0.1.0.dist-info/RECORD
