Metadata-Version: 2.4
Name: py-promptkit
Version: 0.1.0
Summary: Config-driven prompt loading and execution for LLM applications.
Author-email: Adit Bajaj <randomemail@gmail.com>
Classifier: License :: OSI Approved :: MIT License
Classifier: Programming Language :: Python :: 3
Classifier: Programming Language :: Python :: 3.10
Classifier: Programming Language :: Python :: 3.11
Classifier: Programming Language :: Python :: 3.12
Classifier: Intended Audience :: Developers
Classifier: Topic :: Software Development :: Libraries
Requires-Python: >=3.11
License-File: LICENSE
Requires-Dist: flask==3.1.2
Requires-Dist: pydantic==2.12.4
Requires-Dist: litellm==1.79.1
Requires-Dist: requests==2.32.5
Requires-Dist: jsonschema==4.25.1
Requires-Dist: python-dotenv==1.2.1
Requires-Dist: typing-extensions>=4.8.0
Provides-Extra: dev
Requires-Dist: pytest==8.4.2; extra == "dev"
Requires-Dist: ruff==0.14.3; extra == "dev"
Requires-Dist: pylyzer==0.0.82; extra == "dev"
Requires-Dist: iniconfig==2.3.0; extra == "dev"
Requires-Dist: pyright==1.1.407; extra == "dev"
Dynamic: license-file
